google/cloud/language/__init__.py
google/cloud/language/gapic_version.py
google/cloud/language/py.typed
google/cloud/language_v1/__init__.py
google/cloud/language_v1/gapic_metadata.json
google/cloud/language_v1/gapic_version.py
google/cloud/language_v1/py.typed
google/cloud/language_v1/services/__init__.py
google/cloud/language_v1/services/language_service/__init__.py
google/cloud/language_v1/services/language_service/async_client.py
google/cloud/language_v1/services/language_service/client.py
google/cloud/language_v1/services/language_service/transports/__init__.py
google/cloud/language_v1/services/language_service/transports/base.py
google/cloud/language_v1/services/language_service/transports/grpc.py
google/cloud/language_v1/services/language_service/transports/grpc_asyncio.py
google/cloud/language_v1/services/language_service/transports/rest.py
google/cloud/language_v1/services/language_service/transports/rest_base.py
google/cloud/language_v1/types/__init__.py
google/cloud/language_v1/types/language_service.py
google/cloud/language_v1beta2/__init__.py
google/cloud/language_v1beta2/gapic_metadata.json
google/cloud/language_v1beta2/gapic_version.py
google/cloud/language_v1beta2/py.typed
google/cloud/language_v1beta2/services/__init__.py
google/cloud/language_v1beta2/services/language_service/__init__.py
google/cloud/language_v1beta2/services/language_service/async_client.py
google/cloud/language_v1beta2/services/language_service/client.py
google/cloud/language_v1beta2/services/language_service/transports/__init__.py
google/cloud/language_v1beta2/services/language_service/transports/base.py
google/cloud/language_v1beta2/services/language_service/transports/grpc.py
google/cloud/language_v1beta2/services/language_service/transports/grpc_asyncio.py
google/cloud/language_v1beta2/services/language_service/transports/rest.py
google/cloud/language_v1beta2/services/language_service/transports/rest_base.py
google/cloud/language_v1beta2/types/__init__.py
google_cloud_language-2.17.1.dist-info/LICENSE
google_cloud_language-2.17.1.dist-info/METADATA
google_cloud_language-2.17.1.dist-info/WHEEL
google_cloud_language-2.17.1.dist-info/top_level.txt
google_cloud_language-2.17.1.dist-info/RECORD
